[
  {"id": "healingPotion",     "name": "Healing Potion",      "effect": "Restores 8 HP to one ally",                                   "usableIn": ["battle", "prep"], "classRestriction": null},
  {"id": "energyPotion",      "name": "Energy Potion",       "effect": "Restores 6 EN to one ally",                                   "usableIn": ["battle", "prep"], "classRestriction": null},
  {"id": "reviveScroll",      "name": "Revive Scroll",       "effect": "Revives one fallen ally at 1/4 max HP",                       "usableIn": ["battle", "prep"], "classRestriction": null},
  {"id": "speedPotion",       "name": "Speed Potion",        "effect": "+1 DEX permanently for the rest of this run. Stacks.",        "usableIn": ["battle", "prep"], "classRestriction": null},
  {"id": "regenLifePotion",   "name": "Regen Life Potion",   "effect": "+1 HP regen per turn for the rest of this run. Stacks.",      "usableIn": ["battle", "prep"], "classRestriction": null},
  {"id": "regenEnergyPotion", "name": "Regen Energy Potion", "effect": "+1 EN regen per turn for the rest of this run. Stacks.",      "usableIn": ["battle", "prep"], "classRestriction": null}
]
